CHANGES.rst
LICENSE
MANIFEST.in
README.rst
setup.py
examples/etha.com.tr.yaml
examples/torproject.org.yaml
examples/wikipedia.org.yaml
pierky/__init__.py
pierky/ripeatlasmonitor/Action.py
pierky/ripeatlasmonitor/Analyzer.py
pierky/ripeatlasmonitor/Config.py
pierky/ripeatlasmonitor/Errors.py
pierky/ripeatlasmonitor/ExpResCriteria.py
pierky/ripeatlasmonitor/ExpResCriteriaBase.py
pierky/ripeatlasmonitor/ExpResCriteriaCommon.py
pierky/ripeatlasmonitor/ExpResCriteriaDNS.py
pierky/ripeatlasmonitor/ExpResCriteriaDNSRecords.py
pierky/ripeatlasmonitor/ExpResCriteriaSSL.py
pierky/ripeatlasmonitor/ExpResCriteriaTraceroute.py
pierky/ripeatlasmonitor/ExpectedResult.py
pierky/ripeatlasmonitor/Helpers.py
pierky/ripeatlasmonitor/Logging.py
pierky/ripeatlasmonitor/Monitor.py
pierky/ripeatlasmonitor/MsmProcessingUnit.py
pierky/ripeatlasmonitor/ParsedResults.py
pierky/ripeatlasmonitor/Processes.py
pierky/ripeatlasmonitor/Rule.py
pierky/ripeatlasmonitor/__init__.py
pierky/ripeatlasmonitor/doc.py
pierky/ripeatlasmonitor/emailsettings.py
pierky/ripeatlasmonitor/version.py
pierky/ripeatlasmonitor/commands/__init__.py
pierky/ripeatlasmonitor/commands/analyze.py
pierky/ripeatlasmonitor/commands/init_config.py
pierky/ripeatlasmonitor/commands/monitors_management.py
pierky/ripeatlasmonitor/commands/run.py
pierky/ripeatlasmonitor/commands/utils.py
pierky/ripeatlasmonitor/templates/global_config.yaml
ripe_atlas_monitor.egg-info/PKG-INFO
ripe_atlas_monitor.egg-info/SOURCES.txt
ripe_atlas_monitor.egg-info/dependency_links.txt
ripe_atlas_monitor.egg-info/namespace_packages.txt
ripe_atlas_monitor.egg-info/requires.txt
ripe_atlas_monitor.egg-info/top_level.txt
scripts/ripe-atlas-monitor
tests/__init__.py
tests/action_cfg_test.py
tests/action_label_test.py
tests/analyze_test.py
tests/base.py
tests/config_test.py
tests/data.py
tests/doc_test.py
tests/ipcache_test.py
tests/misc_test.py
tests/monitor_cfg_test.py
tests/probes_test.py
tests/results_dns_test.py
tests/results_ping_test.py
tests/results_sslcert_test.py
tests/results_traceroute_test.py
tests/rule_processing_test.py
tests/data/1033154.analyze
tests/data/1033154.json
tests/data/1033154_all_aspath.analyze
tests/data/1033154_all_dstas.analyze
tests/data/1033154_all_rtt.analyze
