Metadata-Version: 1.1
Name: ripe-atlas-monitor
Version: 0.1.10
Summary: A tool to monitor results collected by RIPE Atlas probes and verify they match against predefined expected values.
Home-page: https://github.com/pierky/ripe-atlas-monitor
Author: Pier Carlo Chiodi
Author-email: pierky@pierky.com
License: GPLv3
Download-URL: https://github.com/pierky/ripe-atlas-monitor
Keywords: RIPE,RIPE NCC,RIPE Atlas,Command Line
Platform: UNKNOWN
Classifier: Development Status :: 4 - Beta
Classifier: Environment :: Console
Classifier: Intended Audience :: Information Technology
Classifier: Intended Audience :: Science/Research
Classifier: Intended Audience :: System Administrators
Classifier: Intended Audience :: Telecommunications Industry
Classifier: License :: OSI Approved :: GNU General Public License v3 (GPLv3)
Classifier: Operating System :: POSIX
Classifier: Operating System :: Unix
Classifier: Programming Language :: Python
Classifier: Programming Language :: Python :: 2.7
Classifier: Programming Language :: Python :: 3.4
Classifier: Topic :: Internet :: WWW/HTTP
Classifier: Topic :: System :: Monitoring
Classifier: Topic :: System :: Networking
Classifier: Topic :: System :: Networking :: Monitoring
